djangocms_plugie/__init__.py
djangocms_plugie/apps.py
djangocms_plugie/cms_plugin.py
djangocms_plugie/cms_toolbars.py
djangocms_plugie/config.py
djangocms_plugie/forms.py
djangocms_plugie/setup_script.py
djangocms_plugie/urls.py
djangocms_plugie/utils.py
djangocms_plugie/views.py
djangocms_plugie/exporter/__init__.py
djangocms_plugie/exporter/exporter.py
djangocms_plugie/exporter/field_handler.py
djangocms_plugie/exporter/plugin_serializer.py
djangocms_plugie/importer/__init__.py
djangocms_plugie/importer/version0/__init__.py
djangocms_plugie/importer/version0/importer.py
djangocms_plugie/importer/version0/plugin_context.py
djangocms_plugie/importer/version0/utils.py
djangocms_plugie/importer/version1/__init__.py
djangocms_plugie/importer/version1/importer.py
djangocms_plugie/importer/version1/plugin_context.py
djangocms_plugie/importer/version1/utils.py
djangocms_plugie/methods/__init__.py
djangocms_plugie/methods/built_in_deserializers.py
djangocms_plugie/methods/built_in_serializers.py
djangocms_plugie/methods/exceptions.py
djangocms_plugie/methods/exporter_method_map.py
djangocms_plugie/methods/importer_method_map.py
djangocms_plugie/methods/method_base.py
djangocms_plugie/methods/method_map_base.py
djangocms_plugie/methods/custom_methods/__init__.py
djangocms_plugie/methods/custom_methods/default.py
djangocms_plugie/static/djangocms_plugie/.DS_Store
djangocms_plugie/static/djangocms_plugie/plugie_config.json
djangocms_plugie/static/djangocms_plugie/css/import.css
djangocms_plugie/static/djangocms_plugie/img/icons.png
djangocms_plugie/templates/djangocms_plugie/import_plugins.html
djangocms_plugie/templates/djangocms_plugie/refresh_page.html
djangocms_plugie/tests/__init__.py
djangocms_plugie/tests/filemetadata.py
djangocms_plugie/tests/test_exporter.py
djangocms_plugie/tests/test_forms.py
djangocms_plugie/tests/test_importer_v0.py
djangocms_plugie/tests/test_plugin_serializer.py
djangocms_plugie/tests/test_utils.py
djangocms_plugie-1.0.1.dist-info/LICENSE.md
djangocms_plugie-1.0.1.dist-info/METADATA
djangocms_plugie-1.0.1.dist-info/WHEEL
djangocms_plugie-1.0.1.dist-info/entry_points.txt
djangocms_plugie-1.0.1.dist-info/top_level.txt
djangocms_plugie-1.0.1.dist-info/RECORD
