Metadata-Version: 2.1
Name: djangocms-plugie
Version: 1.0.1
Summary: Export/import django-cms plugins across applications.
Home-page: https://github.com/Formlabs/djangocms-plugie
Author: Alex Costa
Author-email: alexandre.costa@code.berlin
Maintainer: Formlabs Web Team
Maintainer-email: web-software-team@formlabs.com
License: MIT
Classifier: Development Status :: 4 - Beta
Classifier: Environment :: Web Environment
Classifier: Intended Audience :: Developers
Classifier: License :: OSI Approved :: MIT License
Classifier: Operating System :: OS Independent
Classifier: Programming Language :: Python
Classifier: Programming Language :: Python :: 3.8
Classifier: Framework :: Django
Classifier: Framework :: Django :: 1.11
Classifier: Framework :: Django CMS
Classifier: Framework :: Django CMS :: 3.6
License-File: LICENSE.md
Requires-Dist: django-cms >=3.7
Requires-Dist: requests >=2.0
Provides-Extra: dev
